{
  "categories": [
    {
      "id": "2",
      "name": "Hero学习资源",
      "icon": "📚"
    }
  ],
  "websites": [
    {
      "id": "1757732037567",
      "name": "onlyfans",
      "url": "https://onlyfans.com/onlyfans",
      "icon": "",
      "categoryId": "2"
    },
    {
      "id": "1757732133785",
      "name": "pixiv",
      "url": "https://www.pixiv.net/",
      "icon": "",
      "categoryId": "2"
    },
    {
      "id": "1757732182489",
      "name": "pornhub",
      "url": "https://cn.pornhub.com/",
      "icon": "",
      "categoryId": "2"
    },
    {
      "id": "1757732292797",
      "name": "Iwara",
      "url": "https://www.iwara.tv/",
      "icon": "",
      "categoryId": "2"
    },
    {
      "id": "1757732317829",
      "name": "禁漫天堂",
      "url": "https://jmcomic1.ltd/",
      "icon": "",
      "categoryId": "2"
    },
    {
      "id": "1757732390139",
      "name": "Xvidio",
      "url": "https://www.xvideos.com/tags/s:rating/xvidio",
      "icon": "",
      "categoryId": "2"
    },
    {
      "id": "1757732429107",
      "name": "Javbus",
      "url": "https://theporndude.com/zh/2865/javbus",
      "icon": "",
      "categoryId": "2"
    },
    {
      "id": "1757732445809",
      "name": "色花堂",
      "url": "https://xh52.0wxjm.net/",
      "icon": "",
      "categoryId": "2"
    },
    {
      "id": "1757732464127",
      "name": "XNXX",
      "url": "https://www.xnxx.com/",
      "icon": "",
      "categoryId": "2"
    },
    {
      "id": "1757732517754",
      "name": "海角社区",
      "url": "https://haijiao.com/home",
      "icon": "",
      "categoryId": "2"
    },
    {
      "id": "1757732646870",
      "name": "Ehentai",
      "url": "https://e-hentai.org/",
      "icon": "",
      "categoryId": "2"
    },
    {
      "id": "1757732689489",
      "name": "DLsite",
      "url": "https://www.dlsite.com/index.html?locale=zh_CN",
      "icon": "",
      "categoryId": "2"
    },
    {
      "id": "1757732714433",
      "name": "XHAMSTER",
      "url": "https://zh.xhamster.com/",
      "icon": "",
      "categoryId": "2"
    },
    {
      "id": "1757732811349",
      "name": "youporn",
      "url": "https://www.youporn.com/",
      "icon": "",
      "categoryId": "2"
    },
    {
      "id": "1757732843636",
      "name": "chaturbate",
      "url": "https://chaturbate.com/",
      "icon": "",
      "categoryId": "2"
    },
    {
      "id": "1757732862874",
      "name": "bongacams",
      "url": "https://cz.bongacams.com/",
      "icon": "",
      "categoryId": "2"
    },
    {
      "id": "1757732878463",
      "name": "redtube",
      "url": "https://www.redtube.com/",
      "icon": "",
      "categoryId": "2"
    },
    {
      "id": "1757732892442",
      "name": "spankbang",
      "url": "https://spankbang.com/",
      "icon": "",
      "categoryId": "2"
    },
    {
      "id": "1757732953759",
      "name": "H漫",
      "url": "https://hanime1.me/",
      "icon": "",
      "categoryId": "2"
    },
    {
      "id": "1757733107949",
      "name": "ONE",
      "url": "https://9one.app/",
      "icon": "",
      "categoryId": "2"
    },
    {
      "id": "1757733158365",
      "name": "X(twitter)",
      "url": "https://x.com/",
      "icon": "",
      "categoryId": "2"
    },
    {
      "id": "1757733215726",
      "name": "每日大赛",
      "url": "https://uikhct.cc/",
      "icon": "",
      "categoryId": "2"
    },
    {
      "id": "1757733240313",
      "name": "鉴黄师",
      "url": "https://www.javrate.com/",
      "icon": "",
      "categoryId": "2"
    },
    {
      "id": "1757733262897",
      "name": "木瓜视频",
      "url": "https://91quanji.com/",
      "icon": "",
      "categoryId": "2"
    },
    {
      "id": "1757733282984",
      "name": "91吃瓜网",
      "url": "https://6ad.odlfxzn.cc/",
      "icon": "",
      "categoryId": "2"
    },
    {
      "id": "1757733371539",
      "name": "BT漫",
      "url": "https://hentaigasm.com/",
      "icon": "",
      "categoryId": "2"
    },
    {
      "id": "1757733422885",
      "name": "H动漫",
      "url": "https://hentaifreak.org/",
      "icon": "",
      "categoryId": "2"
    },
    {
      "id": "1757733464520",
      "name": "爱恋动漫",
      "url": "http://www.kisssub.org/#continue",
      "icon": "",
      "categoryId": "2"
    },
    {
      "id": "1757733508355",
      "name": "影猫仓库",
      "url": "https://ymck.me/",
      "icon": "",
      "categoryId": "2"
    },
    {
      "id": "1757733547377",
      "name": "NT动漫",
      "url": "https://www.ntdm8.com/",
      "icon": "",
      "categoryId": "2"
    },
    {
      "id": "1757733600761",
      "name": "色批计划",
      "url": "https://spplan.pages.dev/",
      "icon": "",
      "categoryId": "2"
    },
    {
      "id": "1757733649014",
      "name": "种子搜索",
      "url": "https://skrbtiu.top/",
      "icon": "",
      "categoryId": "2"
    },
    {
      "id": "1757733897106",
      "name": "肉不要钱",
      "url": "https://roubuyaoqian.com/",
      "icon": "",
      "categoryId": "2"
    }
  ]
}